Metadata-Version: 2.1
Name: django-polaris
Version: 2.5.0
Summary: An extendable Django server for Stellar Ecosystem Proposals.
Home-page: https://github.com/stellar/django-polaris
License: Apache-2.0
Keywords: stellar,anchor,polaris,sep,server
Author: Stellar Development Foundation
Author-email: jake@stellar.org
Requires-Python: >=3.8,<4.0
Classifier: Environment :: Web Environment
Classifier: Framework :: Django
Classifier: Framework :: Django :: 3.2
Classifier: Intended Audience :: Developers
Classifier: License :: OSI Approved :: Apache Software License
Classifier: Operating System :: OS Independent
Classifier: Programming Language :: Python
Classifier: Programming Language :: Python :: 3
Classifier: Programming Language :: Python :: 3.8
Classifier: Programming Language :: Python :: 3.9
Classifier: Programming Language :: Python :: 3.10
Classifier: Programming Language :: Python :: 3.11
Classifier: Programming Language :: Python :: 3.12
Classifier: Programming Language :: Python :: 3 :: Only
Classifier: Programming Language :: Python :: 3.7
Provides-Extra: dev-server
Provides-Extra: docs
Requires-Dist: aiohttp (>=3.7,<4.0)
Requires-Dist: asgiref (>=3.2,<4.0)
Requires-Dist: cryptography (>=41.0,<42.0)
Requires-Dist: django (>=3.2,<4.0)
Requires-Dist: django-cors-headers (>=3.7,<4.0)
Requires-Dist: django-environ
Requires-Dist: django-model-utils (>=4.1,<5.0)
Requires-Dist: djangorestframework (>=3.12,<4.0)
Requires-Dist: gunicorn ; extra == "dev-server"
Requires-Dist: psycopg2-binary (>=2.9,<3.0) ; extra == "dev-server"
Requires-Dist: pyjwt (>=2.1,<3.0)
Requires-Dist: readthedocs-sphinx-ext (>=2.1,<3.0) ; extra == "docs"
Requires-Dist: sphinx (>=4.2,<5.0) ; extra == "docs"
Requires-Dist: sphinx-autodoc-typehints ; extra == "docs"
Requires-Dist: sphinx-rtd-theme (>=1.0,<2.0) ; extra == "docs"
Requires-Dist: sqlparse (>=0.4.2,<0.5.0)
Requires-Dist: stellar-sdk[aiohttp] (>=10.0.0,<11.0.0)
Requires-Dist: toml
Requires-Dist: watchdog (>=2,<3) ; extra == "dev-server"
Requires-Dist: whitenoise (>=5.3,<6.0)
Project-URL: Bug Tracker, https://github.com/stellar/django-polaris/issues
Project-URL: Documentation, https://django-polaris.readthedocs.io/en/stable
Project-URL: Repository, https://github.com/stellar/django-polaris
Project-URL: Release Notes, https://github.com/stellar/django-polaris/releases
